registro/__init__.py
registro/decorators.py
registro/resource.py
registro/resource_based.py
registro/config/__init__.py
registro/config/settings.py
registro/core/__init__.py
registro/core/resource.py
registro/core/resource_base.py
registro/models/__init__.py
registro/models/auto_nested.py
registro/models/database.py
registro/models/patterns.py
registro/models/rid.py
registro/utils/__init__.py
registro-0.2.2.dist-info/METADATA
registro-0.2.2.dist-info/WHEEL
registro-0.2.2.dist-info/RECORD
