Metadata-Version: 2.4
Name: registro
Version: 0.2.2
Summary: Resource-based model system for SQLModel with automatic Resource creation and validation
Project-URL: Homepage, https://github.com/simbolico/registro
Project-URL: Bug Tracker, https://github.com/simbolico/registro/issues
Project-URL: Documentation, https://simbolico.github.io/registro
Project-URL: Source Code, https://github.com/simbolico/registro
Author-email: Kevin Saltarelli <kevinqz@gmail.com>
License: MIT
Keywords: models,pydantic,resources,sqlalchemy,sqlmodel
Classifier: Development Status :: 4 - Beta
Classifier: Intended Audience :: Developers
Classifier: License :: OSI Approved :: MIT License
Classifier: Programming Language :: Python :: 3
Classifier: Programming Language :: Python :: 3.8
Classifier: Programming Language :: Python :: 3.9
Classifier: Programming Language :: Python :: 3.10
Classifier: Programming Language :: Python :: 3.11
Classifier: Topic :: Database
Classifier: Topic :: Software Development :: Libraries
Requires-Python: >=3.8
Requires-Dist: pydantic>=2.0.0
Requires-Dist: sqlmodel>=0.0.8
Requires-Dist: ulid-py>=1.1.0
Provides-Extra: dev
Requires-Dist: black>=23.3.0; extra == 'dev'
Requires-Dist: isort>=5.12.0; extra == 'dev'
Requires-Dist: mypy>=1.3.0; extra == 'dev'
Requires-Dist: pytest-cov>=4.0.0; extra == 'dev'
Requires-Dist: pytest>=7.0.0; extra == 'dev'
Requires-Dist: ruff>=0.0.272; extra == 'dev'
Provides-Extra: docs
Requires-Dist: mkdocs-material>=9.1.17; extra == 'docs'
Requires-Dist: mkdocs>=1.4.3; extra == 'docs'
Requires-Dist: mkdocstrings[python]>=0.22.0; extra == 'docs'
